{
    "sway/workspaces": {
        "all-outputs": true,
        "format": "{icon}",
        "persistent_workspaces": {
            "1": [],
            "2": [],
            "3": [],
            "4": [],
            "5": [],
            "6": [],
            "7": [],
            "8": [],
            "9": [],
            "10": []
        },
        /* "format-icons": {
          "default": "п„Њ",
          "urgent": "п„Њ",
          "focused": "п†’"
        },*/
        "format-icons": {
            "1": "I",
            "2": "II",
            "3": "III",
            "4": "IV",
            "5": "V",
            "6": "VI",
            "7": "VII",
            "8": "VIII",
            "9": "IX",
            "10": "X"
        },
    },
    "sway/window": {
        "format": "<span>у°…¬ </span> {}",
        "max-length": 100
    },
    "clock": {
        "format": "{:%H:%M}",
        "format-alt": "{:%a, %d. %b %Y - %H:%M}"
    },
    "network": {
        "format": "пЃ±  Disabled",
        "format-wifi": "п‡«  {signalStrength}%",
        "tooltip-format-wifi": "{essid}",
        "format-ethernet": "пѓЃ  {ipaddr}",
        "tooltip-format-ethernet": "{ifname}: {ipaddr}/{cidr}",
        "format-disconnected": "пЃ±  Disconnected",
        "on-click": "footclient -T waybar_nmtui -e nmtui",
        "interval": 2,
    },
    "custom/updates": {
        "format": "{} {icon}",
        "return-type": "json",
        "format-icons": {
            "has-updates": "пЂЎ",
            "updated": "пЃ†"
        },
        "exec-if": "which waybar-module-pacman-updates",
        "exec": "waybar-module-pacman-updates",
    },
    "sway/language": {
        "format": "п„њ {short}",
        "on-click": "~/.config/waybar/scripts/keyhint.sh",
    },
    "cpu": {
        "format": "п’ј{usage: >3}%",
        "on-click": "footclient -T waybar_btop -e btop"
    },
    "memory": {
        "format": "о‰¦ {: >3}%",
        "on-click": "footclient -T waybar_btop -e btop"
    },
    "temperature": {
        "critical-threshold": 80,
        "format-critical": "п‹‡ {temperatureC}В°",
        "format": "п‹‰ {temperatureC}В°",
        "tooltip-format": "{temperatureC}В° Celsius\n{temperatureF}В° Fahrenheit\n{temperatureK}В° Kelvin",
        "hwmon-path": "/sys/devices/pci0000:00/0000:00:18.3/hwmon/hwmon3/temp1_input",
        "on-click": "footclient -T waybar_btop -e btop"
    },
    "backlight": {
        "format": "{icon}{percent: >3}%",
        "format-icons": [
            "п†…",
            "п„‘"
        ],
        "tooltip-format": "Backlight (Scroll): {percent: >3}%",
        "on-scroll-down": "brightnessctl -c backlight set 5%-",
        "on-scroll-up": "brightnessctl -c backlight set +5%"
    },
    "pulseaudio": {
        "scroll-step": 5,
        "format": "{icon}{volume: >3}%",
        "format-bluetooth": "{icon}{volume: >3}%",
        "format-muted": "пЂ¦ muted",
        "format-icons": {
            "headphones": "пЂҐ",
            "handsfree": "пЂҐ",
            "headset": "пЂҐ",
            "phone": "п‚•",
            "portable": "п‚•",
            "car": "п†№",
            "default": [
                "пЂ§",
                "пЂЁ"
            ]
        },
        "on-click": "footclient -T waybar_alsamixer -e alsamixer -M"
    },
    "battery": {
        "states": {
            "warning": 30,
            "critical": 15
        },
        "format": "{icon}{capacity: >3}%",
        "format-icons": [
            "п‰„",
            "п‰ѓ",
            "п‰‚",
            "п‰Ѓ",
            "п‰Ђ"
        ]
    },
    "clock": {
        "format": "<span>пЂ—  </span>{:%a %d %H:%M}",
        "tooltip-format": "<big>{:%Y %B}</big>\n<tt><small> {calendar}</small></tt>"
    },
    "tray": {
        "icon-size": 22
    },
}
